devcontainer_manager/__init__.py
devcontainer_manager/__main__.py
devcontainer_manager/alias.py
devcontainer_manager/base_config.py
devcontainer_manager/config.py
devcontainer_manager/exceptions.py
devcontainer_manager/global_config.py
devcontainer_manager/settings.py
devcontainer_manager/types.py
devcontainer_manager/util.py
devcontainer_manager/yaml.py
devcontainer_manager/cli/__init__.py
devcontainer_manager/cli/alias.py
devcontainer_manager/cli/cli.py
devcontainer_manager/templates/{{ cookiecutter.project_path }}/.devcontainer/build.sh
devcontainer_manager/templates/{{ cookiecutter.project_path }}/.devcontainer/devcontainer.Dockerfile
devcontainer_manager/templates/{{ cookiecutter.project_path }}/.devcontainer/devcontainer.json
devcontainer_manager-1.4.2.dist-info/licenses/LICENSE
devcontainer_manager-1.4.2.dist-info/METADATA
devcontainer_manager-1.4.2.dist-info/WHEEL
devcontainer_manager-1.4.2.dist-info/entry_points.txt
devcontainer_manager-1.4.2.dist-info/top_level.txt
devcontainer_manager-1.4.2.dist-info/RECORD
