Metadata-Version: 2.4
Name: devcontainer_manager
Version: 1.4.2
Home-page: https://github.com/gnox/devcontainer-manager
Author: gnox
License: MIT
Requires-Python: >=3.6
License-File: LICENSE
Requires-Dist: typer>=0.4.0
Requires-Dist: cookiecutter>=1.7.0
Requires-Dist: ruamel.yaml>=0.17.0
Requires-Dist: pydantic<2,>=1.9.0
Requires-Dist: pydantic-yaml<1,>=0.6.3
Provides-Extra: dev
Requires-Dist: pytest; extra == "dev"
Requires-Dist: pre-commit; extra == "dev"
Requires-Dist: twine; extra == "dev"
Dynamic: author
Dynamic: description
Dynamic: description-content-type
Dynamic: home-page
Dynamic: license
Dynamic: license-file
Dynamic: provides-extra
Dynamic: requires-dist
Dynamic: requires-python
